django_pagination_utils/__init__.py
django_pagination_utils/paginator_view.py
django_pagination_utils/mixins/__init__.py
django_pagination_utils/mixins/query_filter_mixin.py
django_pagination_utils/mixins/query_filter_order_mixin.py
django_pagination_utils/mixins/query_order_mixin.py
django_pagination_utils-0.1.5.dist-info/licenses/LICENSE
django_pagination_utils-0.1.5.dist-info/METADATA
django_pagination_utils-0.1.5.dist-info/WHEEL
django_pagination_utils-0.1.5.dist-info/top_level.txt
django_pagination_utils-0.1.5.dist-info/RECORD
