Metadata-Version: 2.4
Name: django-pagination-utils
Version: 0.1.5
Summary: Django pagination utils
Author-email: cristianCEM <cristianbcer27@gmail.com>
License-Expression: MIT
Project-URL: Homepage, https://github.com/cristhianCEM/django-paginations-utils
Keywords: Django,Pagination,Filters
Classifier: Environment :: Web Environment
Classifier: Framework :: Django
Classifier: Framework :: Django :: 5.0
Classifier: Intended Audience :: Developers
Classifier: Operating System :: OS Independent
Classifier: Programming Language :: Python
Classifier: Programming Language :: Python :: 3
Requires-Python: >=3.10
License-File: LICENSE
Requires-Dist: Django>=5.0.0
Requires-Dist: django-filter>=2.4.0
Dynamic: license-file
